CHANGELOG.md
LICENSE
README.md
examples/README.md
lsm6ds3/__init__.py
lsm6ds3-0.0.2.dist-info/METADATA
lsm6ds3-0.0.2.dist-info/WHEEL
lsm6ds3-0.0.2.dist-info/licenses/LICENSE
lsm6ds3-0.0.2.dist-info/RECORD
