Metadata-Version: 2.3
Name: lsm6ds3
Version: 0.0.2
Summary: Python library for the LSM6DS3
Project-URL: GitHub, https://www.github.com/pimoroni/lsm6ds3-python
Project-URL: Homepage, https://www.pimoroni.com
Author-email: Ryan H <ryan@pimoroni.com>
Maintainer-email: Ryan H <ryan@pimoroni.com>
License: MIT License
License-File: LICENSE
Keywords: Pi,Raspberry
Classifier: Intended Audience :: Developers
Classifier: License :: OSI Approved :: MIT License
Classifier: Operating System :: POSIX :: Linux
Classifier: Programming Language :: Python :: 3
Classifier: Programming Language :: Python :: 3 :: Only
Classifier: Programming Language :: Python :: 3.7
Classifier: Programming Language :: Python :: 3.8
Classifier: Programming Language :: Python :: 3.9
Classifier: Programming Language :: Python :: 3.10
Classifier: Programming Language :: Python :: 3.11
Classifier: Topic :: Software Development
Classifier: Topic :: Software Development :: Libraries
Classifier: Topic :: System :: Hardware
Requires-Python: >=3.7
Requires-Dist: i2cdevice>=1.0.0
Requires-Dist: smbus2>=0.4.3
